uvnb/__init__.py
uvnb/__main__.py
uvnb-0.1.0.dist-info/LICENSE
uvnb-0.1.0.dist-info/METADATA
uvnb-0.1.0.dist-info/WHEEL
uvnb-0.1.0.dist-info/entry_points.txt
uvnb-0.1.0.dist-info/top_level.txt
uvnb-0.1.0.dist-info/RECORD
