Metadata-Version: 2.1
Name: uvnb
Version: 0.1.0
Summary: A utility to run UV against Jupyter notebooks
Project-URL: Homepage, https://github.com/koaning/uvnb
Project-URL: Repository, https://github.com/koaning/uvnb.git
Classifier: Programming Language :: Python :: 3
Classifier: License :: OSI Approved :: MIT License
Classifier: Operating System :: OS Independent
Requires-Python: >=3.11
License-File: LICENSE
Requires-Dist: click
Requires-Dist: uv
Requires-Dist: nbformat
Requires-Dist: nbconvert
